odoo/addons/ssi_sale_canvas/README.rst
odoo/addons/ssi_sale_canvas/__init__.py
odoo/addons/ssi_sale_canvas/__manifest__.py
odoo/addons/ssi_sale_canvas/menu.xml
odoo/addons/ssi_sale_canvas/data/approval_template_data.xml
odoo/addons/ssi_sale_canvas/data/base_automation_data.xml
odoo/addons/ssi_sale_canvas/data/ir_actions_server_data.xml
odoo/addons/ssi_sale_canvas/data/ir_sequence_data.xml
odoo/addons/ssi_sale_canvas/data/policy_template_data.xml
odoo/addons/ssi_sale_canvas/data/sequence_template_data.xml
odoo/addons/ssi_sale_canvas/models/__init__.py
odoo/addons/ssi_sale_canvas/models/sale_canvas.py
odoo/addons/ssi_sale_canvas/models/sale_canvas_line.py
odoo/addons/ssi_sale_canvas/models/sale_canvas_realization_header.py
odoo/addons/ssi_sale_canvas/models/sale_canvas_realization_line.py
odoo/addons/ssi_sale_canvas/models/sale_canvas_type.py
odoo/addons/ssi_sale_canvas/models/stock_move.py
odoo/addons/ssi_sale_canvas/models/stock_rule.py
odoo/addons/ssi_sale_canvas/security/ir.model.access.csv
odoo/addons/ssi_sale_canvas/security/ir_module_category_data.xml
odoo/addons/ssi_sale_canvas/security/ir_rule_data.xml
odoo/addons/ssi_sale_canvas/security/res_group_data.xml
odoo/addons/ssi_sale_canvas/static/description/icon.png
odoo/addons/ssi_sale_canvas/views/sale_canvas_type_views.xml
odoo/addons/ssi_sale_canvas/views/sale_canvas_views.xml
odoo14_addon_ssi_sale_canvas-14.0.1.3.1.dist-info/METADATA
odoo14_addon_ssi_sale_canvas-14.0.1.3.1.dist-info/WHEEL
odoo14_addon_ssi_sale_canvas-14.0.1.3.1.dist-info/top_level.txt
odoo14_addon_ssi_sale_canvas-14.0.1.3.1.dist-info/RECORD
